bitcoin_message_tool/__init__.py
bitcoin_message_tool/__main__.py
bitcoin_message_tool/bmt.py
bitcoin_message_tool-0.1.4.dist-info/METADATA
bitcoin_message_tool-0.1.4.dist-info/entry_points.txt
bitcoin_message_tool-0.1.4.dist-info/WHEEL
bitcoin_message_tool-0.1.4.dist-info/LICENSE.txt
bitcoin_message_tool-0.1.4.dist-info/RECORD
