Metadata-Version: 2.1
Name: bitcoin-message-tool
Version: 0.1.4
Summary: Bitcoin message signing/verification tool
Author: shadowy-pycoder
Author-email: shadowy-pycoder@example.com
Requires-Python: >=3.10,<4.0
Classifier: License :: OSI Approved :: MIT License
Classifier: Operating System :: OS Independent
Classifier: Programming Language :: Python :: 3
Classifier: Programming Language :: Python :: 3.10
Classifier: Programming Language :: Python :: 3.11
Classifier: Programming Language :: Python :: 3
Requires-Dist: base58 (>=2.1.1,<3.0.0)
Requires-Dist: bech32 (>=1.2.0,<2.0.0)
Requires-Dist: pytest (>=7.2.1,<8.0.0)
Requires-Dist: ripemd-hash (>=1.0.0,<2.0.0)
